dbt/__init__.py
dbt/adapters/__init__.py
dbt/adapters/postgres/__init__.py
dbt/adapters/postgres/__version__.py
dbt/adapters/postgres/connections.py
dbt/adapters/postgres/impl.py
dbt/adapters/postgres/relation.py
dbt/include/opengauss/__init__.py
dbt/include/opengauss/dbt_project.yml
dbt/include/opengauss/sample_profiles.yml
dbt/include/opengauss/macros/adapters.sql
dbt/include/opengauss/macros/catalog.sql
dbt/include/opengauss/macros/relations.sql
dbt/include/opengauss/macros/materializations/snapshot_merge.sql
dbt/include/opengauss/macros/utils/any_value.sql
dbt/include/opengauss/macros/utils/dateadd.sql
dbt/include/opengauss/macros/utils/datediff.sql
dbt/include/opengauss/macros/utils/last_day.sql
dbt/include/opengauss/macros/utils/listagg.sql
dbt/include/opengauss/macros/utils/split_part.sql
dbt_opengauss-1.0.1.dist-info/METADATA
dbt_opengauss-1.0.1.dist-info/WHEEL
dbt_opengauss-1.0.1.dist-info/top_level.txt
dbt_opengauss-1.0.1.dist-info/RECORD
