Metadata-Version: 2.1
Name: dbt-opengauss
Version: 1.0.1
Summary: The opengauss adapter plugin for dbt (data build tool)
Home-page: https://github.com/zEpoch
Author: ZhouTao
Author-email: zhotoa@foxmail.com
Classifier: Development Status :: 5 - Production/Stable
Classifier: License :: OSI Approved :: Apache Software License
Classifier: Operating System :: Microsoft :: Windows
Classifier: Operating System :: MacOS :: MacOS X
Classifier: Operating System :: POSIX :: Linux
Classifier: Programming Language :: Python :: 3.7
Classifier: Programming Language :: Python :: 3.8
Classifier: Programming Language :: Python :: 3.9
Classifier: Programming Language :: Python :: 3.10
Requires-Python: >=3.7
Requires-Dist: dbt-core (==1.0.1)
Requires-Dist: psycopg2-binary (~=2.8)
